radio_gyms/__init__.py
radio_gyms/engines/__init__.py
radio_gyms/engines/ray_tracer/__init__.py
radio_gyms/engines/ray_tracer/box.py
radio_gyms/engines/ray_tracer/bvh.py
radio_gyms/engines/ray_tracer/obj_reader.py
radio_gyms/engines/ray_tracer/tracer.py
radio_gyms/engines/ray_tracer/triangle.py
radio_gyms/gyms/__init__.py
radio_gyms/gyms/base.py
radio_gyms/gyms/location_gym.py
radio_gyms/models/__init__.py
radio_gyms/models/hata_okumura.py
radio_gyms/models/theoretical.py
radio_gyms/objects/__init__.py
radio_gyms/objects/cell.py
radio_gyms/objects/pedestrian.py
radio_gyms/objects/receiver.py
radio_gyms/objects/transmitter.py
radio_gyms/simulations/__init__.py
radio_gyms/simulations/oldtown_walk.py
radio_gyms/utils/__init__.py
radio_gyms/utils/calculations.py
radio_gyms/utils/constants.py
radio_gyms/utils/converters.py
radio_gyms/utils/notebook.py
radio_gyms/utils/plotter.py
radio_gyms/visualizers/__init__.py
radio_gyms/visualizers/visual_triangle.py
radio_gyms/visualizers/window.py
test/__init__.py
test/test_gyms.py
test/test_model_outdoor.py
test/test_notebook.py
test/test_performance.py
test/test_simulation_oldtown.py
test/test_tracer.py
test/test_utils.py
test/test_version.py
test/test_virtualizer.py
radio_gyms-0.7.0.dist-info/LICENSE
radio_gyms-0.7.0.dist-info/METADATA
radio_gyms-0.7.0.dist-info/WHEEL
radio_gyms-0.7.0.dist-info/top_level.txt
radio_gyms-0.7.0.dist-info/RECORD
