Metadata-Version: 2.1
Name: radio-gyms
Version: 0.7.0
Summary: an open-source bundle of AI environments for radio communications
Home-page: https://github.com/intelek-ai/radio-gyms
Author: Intelek AI
Author-email: supawat@intelek.ai
License: MIT
Project-URL: Bug Tracker, https://github.com/intelek-ai/radio-gyms/issues
Project-URL: Documentations, https://radio-gyms.intelek.ai
Platform: UNKNOWN
Classifier: Programming Language :: Python :: 3
Classifier: License :: OSI Approved :: MIT License
Classifier: Operating System :: OS Independent
Classifier: Topic :: Scientific/Engineering :: Artificial Intelligence
Classifier: Intended Audience :: Science/Research
Classifier: Intended Audience :: Telecommunications Industry
Classifier: Topic :: Games/Entertainment :: Simulation
Requires-Python: >=3.8
License-File: LICENSE
